Metadata-Version: 2.4
Name: choreographer
Version: 1.0.8
Summary: Devtools Protocol implementation for chrome.
Author-email: Andrew Pikul <ajpikul@gmail.com>, Neyberson Atencio <neyberatencio@gmail.com>
Maintainer-email: Andrew Pikul <ajpikul@gmail.com>
Project-URL: Homepage, https://github.com/plotly/choreographer
Project-URL: Repository, https://github.com/plotly/choreographer
Requires-Python: >=3.8
License-File: LICENSE.md
Requires-Dist: logistro>=1.0.11
Requires-Dist: simplejson>=3.19.3
Dynamic: license-file
